hwo_disra/Brown_Dwarfs_Smart_2019.csv
hwo_disra/DRMinator.py
hwo_disra/EAC.py
hwo_disra/Plotinator.py
hwo_disra/Resolvinator.py
hwo_disra/Timeinator.py
hwo_disra/Types.py
hwo_disra/Yieldinator.py
hwo_disra/__init__.py
hwo_disra/environment.py
hwo_disra/matrix_lookup_yieldinator.py
hwo_disra/version.py
hwo_disra/yield_sample.py
hwo_disra/api/__init__.py
hwo_disra/api/notebook_api.py
hwo_disra/api/notebook_eval.py
hwo_disra/api/stm_extractor.py
hwo_disra/data/Brown_Dwarfs_Smart_2019.csv
hwo_disra/data/Brown_Dwarfs_Smart_2019_rejected.csv
hwo_disra/data/README.rst
hwo_disra/data/dr7qso_galex.fits
hwo_disra/data/science-case-trade-spacee-panels.png
hwo_disra/tests/.gitignore
hwo_disra/tests/__init__.py
hwo_disra/tests/conftest.py
hwo_disra/tests/test_integration_stm.py
hwo_disra/tests/test_kbo_yieldinator.py
hwo_disra/tests/test_notebook_eval.py
hwo_disra/tests/test_package_isolation.py
hwo_disra/tests/test_qso_yieldinator.py
hwo_disra/tests/test_resolvinator.py
hwo_disra/tests/test_stellar_evolution_yieldinator.py
hwo_disra/tests/test_stm_extractor.py
hwo_disra/tests/outputs/.gitignore
hwo_disra/tests/resources/.gitignore
hwo_disra/tests/resources/hwo_disra-api-test.ipynb
hwo_disra/tests/resources/hwo_disra_readme.ipynb
hwo_disra/yields/BDYieldinator.py
hwo_disra/yields/KBOYieldinator.py
hwo_disra/yields/QSOYieldinator.py
hwo_disra/yields/StellarEvolution.py
hwo_disra/yields/__init__.py
hwo_disra-0.0.8.dist-info/METADATA
hwo_disra-0.0.8.dist-info/WHEEL
hwo_disra-0.0.8.dist-info/top_level.txt
hwo_disra-0.0.8.dist-info/RECORD
