Metadata-Version: 2.4
Name: hwo_disra
Version: 0.0.8
Author-email: Andrew Myers <amyers@stsci.edu>, Adric Riedel <riedel@stsci.edu>, Nazma Ferdous <ferdous@stsci.edu>, Rachel Vander Vliet <rvandervliet@stsci.edu>, Jason Tumlinson <tumlinson@stsci.edu>
License: Copyright (c) 2025, Jason Tumlinson
Requires-Python: >=3.10
Requires-Dist: syotools==1.3
Requires-Dist: hwo_sci_eng==0.1.9
Requires-Dist: matplotlib
Requires-Dist: jupyter_client
Requires-Dist: nbformat
Requires-Dist: ipykernel
Provides-Extra: test
Requires-Dist: pytest; extra == "test"
Requires-Dist: pytest-cov; extra == "test"
Requires-Dist: hypothesis; extra == "test"
Requires-Dist: uv; extra == "test"
Provides-Extra: docs
Requires-Dist: sphinx; extra == "docs"
Requires-Dist: sphinx-automodapi; extra == "docs"
